secret_store_client/__init__.py
secret_store_client/client.py
ocean_secret_store_client-0.0.2.dist-info/LICENSE
ocean_secret_store_client-0.0.2.dist-info/METADATA
ocean_secret_store_client-0.0.2.dist-info/WHEEL
ocean_secret_store_client-0.0.2.dist-info/top_level.txt
ocean_secret_store_client-0.0.2.dist-info/RECORD
